modelcif/__init__.py
modelcif/alignment.py
modelcif/associated.py
modelcif/data.py
modelcif/descriptor.py
modelcif/dumper.py
modelcif/model.py
modelcif/protocol.py
modelcif/qa_metric.py
modelcif/reader.py
modelcif/reference.py
modelcif/test.py
modelcif/util/__init__.py
modelcif/util/make_mmcif.py
modelcif-1.6.dist-info/licenses/LICENSE
modelcif-1.6.dist-info/METADATA
modelcif-1.6.dist-info/WHEEL
modelcif-1.6.dist-info/top_level.txt
modelcif-1.6.dist-info/RECORD
