Metadata-Version: 2.4
Name: modelcif
Version: 1.6
Summary: Package for handling ModelCIF mmCIF and BinaryCIF files
Home-page: https://github.com/ihmwg/python-modelcif
Author: Ben Webb
Author-email: Ben Webb <benmwebb@gmail.com>
License: MIT
Project-URL: homepage, https://github.com/ihmwg/python-modelcif
Project-URL: repository, https://github.com/ihmwg/python-modelcif
Project-URL: documentation, https://python-modelcif.readthedocs.io/
Project-URL: issues, https://github.com/ihmwg/python-modelcif/issues/
Project-URL: changelog, https://github.com/ihmwg/python-modelcif/blob/main/ChangeLog.rst
Classifier: Programming Language :: Python :: 3
Classifier: Operating System :: OS Independent
Classifier: Intended Audience :: Science/Research
Classifier: Topic :: Scientific/Engineering
Requires-Python: >=3.6
License-File: LICENSE
Requires-Dist: ihm>=2.6
Dynamic: author
Dynamic: home-page
Dynamic: license-file
